[
  {
    "date": "2021-01-01",
    "time": "18:35:08",
    "num": 19
  },
  {
    "date": "2021-01-02",
    "time": "19:56:58",
    "num": 20
  },
  {
    "date": "2021-01-03",
    "time": "21:21:21",
    "num": 21
  },
  {
    "date": "2021-01-04",
    "time": "22:46:26",
    "num": 22
  },
  {
    "date": "2021-01-05",
    "time": "00:00:00",
    "num": 23
  },
  {
    "date": "2021-01-06",
    "time": "00:12:03",
    "num": 23
  },
  {
    "date": "2021-01-07",
    "time": "01:38:59",
    "num": 24
  },
  {
    "date": "2021-01-08",
    "time": "03:08:09",
    "num": 25
  },
  {
    "date": "2021-01-09",
    "time": "04:39:39",
    "num": 26
  },
  {
    "date": "2021-01-10",
    "time": "06:11:19",
    "num": 27
  },
  {
    "date": "2021-01-11",
    "time": "07:37:24",
    "num": 28
  },
  {
    "date": "2021-01-12",
    "time": "08:49:35",
    "num": 29
  },
  {
    "date": "2021-01-13",
    "time": "08:00:04",
    "num": 1
  },
  {
    "date": "2021-01-13",
    "time": "09:42:36",
    "num": 2
  },
  {
    "date": "2021-01-14",
    "time": "10:18:24",
    "num": 3
  },
  {
    "date": "2021-01-15",
    "time": "10:42:30",
    "num": 4
  },
  {
    "date": "2021-01-16",
    "time": "10:59:36",
    "num": 5
  },
  {
    "date": "2021-01-17",
    "time": "11:12:43",
    "num": 6
  },
  {
    "date": "2021-01-18",
    "time": "11:23:43",
    "num": 7
  },
  {
    "date": "2021-01-19",
    "time": "11:33:49",
    "num": 8
  },
  {
    "date": "2021-01-20",
    "time": "11:43:59",
    "num": 9
  },
  {
    "date": "2021-01-21",
    "time": "11:55:10",
    "num": 10
  },
  {
    "date": "2021-01-22",
    "time": "12:08:29",
    "num": 11
  },
  {
    "date": "2021-01-23",
    "time": "12:25:26",
    "num": 12
  },
  {
    "date": "2021-01-24",
    "time": "12:48:16",
    "num": 13
  },
  {
    "date": "2021-01-25",
    "time": "13:20:05",
    "num": 14
  },
  {
    "date": "2021-01-26",
    "time": "14:04:31",
    "num": 15
  },
  {
    "date": "2021-01-27",
    "time": "15:03:49",
    "num": 16
  },
  {
    "date": "2021-01-28",
    "time": "16:16:41",
    "num": 17
  },
  {
    "date": "2021-01-29",
    "time": "17:38:36",
    "num": 18
  },
  {
    "date": "2021-01-30",
    "time": "19:04:39",
    "num": 19
  },
  {
    "date": "2021-01-31",
    "time": "20:31:47",
    "num": 20
  },
  {
    "date": "2021-02-01",
    "time": "21:58:55",
    "num": 21
  },
  {
    "date": "2021-02-02",
    "time": "23:26:20",
    "num": 22
  },
  {
    "date": "2021-02-03",
    "time": "00:00:00",
    "num": 22
  },
  {
    "date": "2021-02-04",
    "time": "00:54:47",
    "num": 23
  },
  {
    "date": "2021-02-05",
    "time": "02:24:39",
    "num": 24
  },
  {
    "date": "2021-02-06",
    "time": "03:54:45",
    "num": 25
  },
  {
    "date": "2021-02-07",
    "time": "05:21:08",
    "num": 26
  },
  {
    "date": "2021-02-08",
    "time": "06:36:53",
    "num": 27
  },
  {
    "date": "2021-02-09",
    "time": "07:35:38",
    "num": 28
  },
  {
    "date": "2021-02-10",
    "time": "08:16:43",
    "num": 29
  },
  {
    "date": "2021-02-11",
    "time": "08:44:29",
    "num": 30
  },
  {
    "date": "2021-02-11",
    "time": "22:05:34",
    "num": 1
  },
  {
    "date": "2021-02-12",
    "time": "09:03:51",
    "num": 2
  },
  {
    "date": "2021-02-13",
    "time": "09:18:17",
    "num": 3
  },
  {
    "date": "2021-02-14",
    "time": "09:29:57",
    "num": 4
  },
  {
    "date": "2021-02-15",
    "time": "09:40:17",
    "num": 5
  },
  {
    "date": "2021-02-16",
    "time": "09:50:16",
    "num": 6
  },
  {
    "date": "2021-02-17",
    "time": "10:00:51",
    "num": 7
  },
  {
    "date": "2021-02-18",
    "time": "10:13:00",
    "num": 8
  },
  {
    "date": "2021-02-19",
    "time": "10:28:01",
    "num": 9
  },
  {
    "date": "2021-02-20",
    "time": "10:47:45",
    "num": 10
  },
  {
    "date": "2021-02-21",
    "time": "11:14:52",
    "num": 11
  },
  {
    "date": "2021-02-22",
    "time": "11:52:54",
    "num": 12
  },
  {
    "date": "2021-02-23",
    "time": "12:45:05",
    "num": 13
  },
  {
    "date": "2021-02-24",
    "time": "13:52:12",
    "num": 14
  },
  {
    "date": "2021-02-25",
    "time": "15:11:15",
    "num": 15
  },
  {
    "date": "2021-02-26",
    "time": "16:37:22",
    "num": 16
  },
  {
    "date": "2021-02-27",
    "time": "18:06:28",
    "num": 17
  },
  {
    "date": "2021-02-28",
    "time": "19:36:28",
    "num": 18
  },
  {
    "date": "2021-03-01",
    "time": "21:06:51",
    "num": 19
  },
  {
    "date": "2021-03-02",
    "time": "22:37:59",
    "num": 20
  },
  {
    "date": "2021-03-04",
    "time": "00:10:07",
    "num": 21
  },
  {
    "date": "2021-03-05",
    "time": "01:42:19",
    "num": 22
  },
  {
    "date": "2021-03-06",
    "time": "03:11:14",
    "num": 23
  },
  {
    "date": "2021-03-07",
    "time": "04:30:39",
    "num": 24
  },
  {
    "date": "2021-03-08",
    "time": "05:33:50",
    "num": 25
  },
  {
    "date": "2021-03-09",
    "time": "06:18:49",
    "num": 26
  },
  {
    "date": "2021-03-10",
    "time": "06:49:13",
    "num": 27
  },
  {
    "date": "2021-03-11",
    "time": "07:10:07",
    "num": 28
  },
  {
    "date": "2021-03-12",
    "time": "07:25:22",
    "num": 29
  },
  {
    "date": "2021-03-13",
    "time": "07:37:24",
    "num": 30
  },
  {
    "date": "2021-03-13",
    "time": "13:21:03",
    "num": 1
  },
  {
    "date": "2021-03-14",
    "time": "07:47:43",
    "num": 2
  },
  {
    "date": "2021-03-15",
    "time": "07:57:26",
    "num": 3
  },
  {
    "date": "2021-03-16",
    "time": "08:07:24",
    "num": 4
  },
  {
    "date": "2021-03-17",
    "time": "08:18:33",
    "num": 5
  },
  {
    "date": "2021-03-18",
    "time": "08:31:57",
    "num": 6
  },
  {
    "date": "2021-03-19",
    "time": "08:49:11",
    "num": 7
  },
  {
    "date": "2021-03-20",
    "time": "09:12:27",
    "num": 8
  },
  {
    "date": "2021-03-21",
    "time": "09:44:51",
    "num": 9
  },
  {
    "date": "2021-03-22",
    "time": "10:29:50",
    "num": 10
  },
  {
    "date": "2021-03-23",
    "time": "11:29:25",
    "num": 11
  },
  {
    "date": "2021-03-24",
    "time": "12:42:24",
    "num": 12
  },
  {
    "date": "2021-03-25",
    "time": "14:04:52",
    "num": 13
  },
  {
    "date": "2021-03-26",
    "time": "15:32:37",
    "num": 14
  },
  {
    "date": "2021-03-27",
    "time": "17:02:58",
    "num": 15
  },
  {
    "date": "2021-03-28",
    "time": "18:34:52",
    "num": 16
  },
  {
    "date": "2021-03-29",
    "time": "20:08:21",
    "num": 17
  },
  {
    "date": "2021-03-30",
    "time": "21:43:43",
    "num": 18
  },
  {
    "date": "2021-03-31",
    "time": "23:20:14",
    "num": 19
  },
  {
    "date": "2021-04-02",
    "time": "00:54:56",
    "num": 20
  },
  {
    "date": "2021-04-03",
    "time": "02:21:29",
    "num": 21
  },
  {
    "date": "2021-04-04",
    "time": "03:31:55",
    "num": 22
  },
  {
    "date": "2021-04-05",
    "time": "04:22:26",
    "num": 23
  },
  {
    "date": "2021-04-06",
    "time": "04:56:05",
    "num": 24
  },
  {
    "date": "2021-04-07",
    "time": "05:18:38",
    "num": 25
  },
  {
    "date": "2021-04-08",
    "time": "05:34:36",
    "num": 26
  },
  {
    "date": "2021-04-09",
    "time": "05:46:50",
    "num": 27
  },
  {
    "date": "2021-04-10",
    "time": "05:57:04",
    "num": 28
  },
  {
    "date": "2021-04-11",
    "time": "06:06:26",
    "num": 29
  },
  {
    "date": "2021-04-12",
    "time": "05:30:44",
    "num": 1
  },
  {
    "date": "2021-04-12",
    "time": "06:15:49",
    "num": 2
  },
  {
    "date": "2021-04-13",
    "time": "06:26:04",
    "num": 3
  },
  {
    "date": "2021-04-14",
    "time": "06:38:12",
    "num": 4
  },
  {
    "date": "2021-04-15",
    "time": "06:53:30",
    "num": 5
  },
  {
    "date": "2021-04-16",
    "time": "07:13:53",
    "num": 6
  },
  {
    "date": "2021-04-17",
    "time": "07:42:04",
    "num": 7
  },
  {
    "date": "2021-04-18",
    "time": "08:21:19",
    "num": 8
  },
  {
    "date": "2021-04-19",
    "time": "09:14:13",
    "num": 9
  },
  {
    "date": "2021-04-20",
    "time": "10:20:42",
    "num": 10
  },
  {
    "date": "2021-04-21",
    "time": "11:37:44",
    "num": 11
  },
  {
    "date": "2021-04-22",
    "time": "13:01:20",
    "num": 12
  },
  {
    "date": "2021-04-23",
    "time": "14:28:35",
    "num": 13
  },
  {
    "date": "2021-04-24",
    "time": "15:58:15",
    "num": 14
  },
  {
    "date": "2021-04-25",
    "time": "17:30:22",
    "num": 15
  },
  {
    "date": "2021-04-26",
    "time": "19:05:31",
    "num": 16
  },
  {
    "date": "2021-04-27",
    "time": "20:43:50",
    "num": 17
  },
  {
    "date": "2021-04-28",
    "time": "22:23:26",
    "num": 18
  },
  {
    "date": "2021-04-29",
    "time": "23:58:45",
    "num": 19
  },
  {
    "date": "2021-05-01",
    "time": "01:20:24",
    "num": 20
  },
  {
    "date": "2021-05-02",
    "time": "02:20:49",
    "num": 21
  },
  {
    "date": "2021-05-03",
    "time": "03:00:46",
    "num": 22
  },
  {
    "date": "2021-05-04",
    "time": "03:26:36",
    "num": 23
  },
  {
    "date": "2021-05-05",
    "time": "03:44:09",
    "num": 24
  },
  {
    "date": "2021-05-06",
    "time": "03:57:04",
    "num": 25
  },
  {
    "date": "2021-05-07",
    "time": "04:07:28",
    "num": 26
  },
  {
    "date": "2021-05-08",
    "time": "04:16:42",
    "num": 27
  },
  {
    "date": "2021-05-09",
    "time": "04:25:41",
    "num": 28
  },
  {
    "date": "2021-05-10",
    "time": "04:35:17",
    "num": 29
  },
  {
    "date": "2021-05-11",
    "time": "04:46:24",
    "num": 30
  },
  {
    "date": "2021-05-11",
    "time": "21:59:41",
    "num": 1
  },
  {
    "date": "2021-05-12",
    "time": "05:00:15",
    "num": 2
  },
  {
    "date": "2021-05-13",
    "time": "05:18:30",
    "num": 3
  },
  {
    "date": "2021-05-14",
    "time": "05:43:34",
    "num": 4
  },
  {
    "date": "2021-05-15",
    "time": "06:18:36",
    "num": 5
  },
  {
    "date": "2021-05-16",
    "time": "07:06:29",
    "num": 6
  },
  {
    "date": "2021-05-17",
    "time": "08:07:55",
    "num": 7
  },
  {
    "date": "2021-05-18",
    "time": "09:20:26",
    "num": 8
  },
  {
    "date": "2021-05-19",
    "time": "10:40:01",
    "num": 9
  },
  {
    "date": "2021-05-20",
    "time": "12:03:26",
    "num": 10
  },
  {
    "date": "2021-05-21",
    "time": "13:29:07",
    "num": 11
  },
  {
    "date": "2021-05-22",
    "time": "14:57:03",
    "num": 12
  },
  {
    "date": "2021-05-23",
    "time": "16:28:05",
    "num": 13
  },
  {
    "date": "2021-05-24",
    "time": "18:03:11",
    "num": 14
  },
  {
    "date": "2021-05-25",
    "time": "19:42:10",
    "num": 15
  },
  {
    "date": "2021-05-26",
    "time": "21:21:51",
    "num": 16
  },
  {
    "date": "2021-05-27",
    "time": "22:54:03",
    "num": 17
  },
  {
    "date": "2021-05-28",
    "time": "00:00:00",
    "num": 17
  },
  {
    "date": "2021-05-29",
    "time": "00:07:48",
    "num": 18
  },
  {
    "date": "2021-05-30",
    "time": "00:58:20",
    "num": 19
  },
  {
    "date": "2021-05-31",
    "time": "01:30:26",
    "num": 20
  },
  {
    "date": "2021-06-01",
    "time": "01:51:18",
    "num": 21
  },
  {
    "date": "2021-06-02",
    "time": "02:05:54",
    "num": 22
  },
  {
    "date": "2021-06-03",
    "time": "02:17:08",
    "num": 23
  },
  {
    "date": "2021-06-04",
    "time": "02:26:40",
    "num": 24
  },
  {
    "date": "2021-06-05",
    "time": "02:35:37",
    "num": 25
  },
  {
    "date": "2021-06-06",
    "time": "02:44:51",
    "num": 26
  },
  {
    "date": "2021-06-07",
    "time": "02:55:17",
    "num": 27
  },
  {
    "date": "2021-06-08",
    "time": "03:08:00",
    "num": 28
  },
  {
    "date": "2021-06-09",
    "time": "03:24:33",
    "num": 29
  },
  {
    "date": "2021-06-10",
    "time": "03:47:07",
    "num": 30
  },
  {
    "date": "2021-06-10",
    "time": "13:52:32",
    "num": 1
  },
  {
    "date": "2021-06-11",
    "time": "04:18:43",
    "num": 2
  },
  {
    "date": "2021-06-12",
    "time": "05:02:33",
    "num": 3
  },
  {
    "date": "2021-06-13",
    "time": "06:00:07",
    "num": 4
  },
  {
    "date": "2021-06-14",
    "time": "07:09:39",
    "num": 5
  },
  {
    "date": "2021-06-15",
    "time": "08:26:59",
    "num": 6
  },
  {
    "date": "2021-06-16",
    "time": "09:48:14",
    "num": 7
  },
  {
    "date": "2021-06-17",
    "time": "11:11:16",
    "num": 8
  },
  {
    "date": "2021-06-18",
    "time": "00:00:00",
    "num": 9
  },
  {
    "date": "2021-06-19",
    "time": "14:02:08",
    "num": 10
  },
  {
    "date": "2021-06-20",
    "time": "15:32:00",
    "num": 11
  },
  {
    "date": "2021-06-21",
    "time": "17:06:07",
    "num": 12
  },
  {
    "date": "2021-06-22",
    "time": "18:43:37",
    "num": 13
  },
  {
    "date": "2021-06-23",
    "time": "20:19:36",
    "num": 14
  },
  {
    "date": "2021-06-24",
    "time": "21:43:59",
    "num": 15
  },
  {
    "date": "2021-06-25",
    "time": "22:47:00",
    "num": 16
  },
  {
    "date": "2021-06-26",
    "time": "23:28:11",
    "num": 17
  },
  {
    "date": "2021-06-27",
    "time": "23:54:20",
    "num": 18
  },
  {
    "date": "2021-06-28",
    "time": "00:00:00",
    "num": 18
  },
  {
    "date": "2021-06-29",
    "time": "00:11:52",
    "num": 19
  },
  {
    "date": "2021-06-30",
    "time": "00:24:41",
    "num": 20
  },
  {
    "date": "2021-07-01",
    "time": "00:35:01",
    "num": 21
  },
  {
    "date": "2021-07-02",
    "time": "00:44:17",
    "num": 22
  },
  {
    "date": "2021-07-03",
    "time": "00:53:27",
    "num": 23
  },
  {
    "date": "2021-07-04",
    "time": "01:03:26",
    "num": 24
  },
  {
    "date": "2021-07-05",
    "time": "01:15:16",
    "num": 25
  },
  {
    "date": "2021-07-06",
    "time": "01:30:20",
    "num": 26
  },
  {
    "date": "2021-07-07",
    "time": "01:50:36",
    "num": 27
  },
  {
    "date": "2021-07-08",
    "time": "02:18:55",
    "num": 28
  },
  {
    "date": "2021-07-09",
    "time": "02:58:39",
    "num": 29
  },
  {
    "date": "2021-07-10",
    "time": "03:52:18",
    "num": 30
  },
  {
    "date": "2021-07-10",
    "time": "04:16:30",
    "num": 1
  },
  {
    "date": "2021-07-11",
    "time": "04:59:12",
    "num": 2
  },
  {
    "date": "2021-07-12",
    "time": "06:15:27",
    "num": 3
  },
  {
    "date": "2021-07-13",
    "time": "07:36:30",
    "num": 4
  },
  {
    "date": "2021-07-14",
    "time": "08:59:19",
    "num": 5
  },
  {
    "date": "2021-07-15",
    "time": "10:22:46",
    "num": 6
  },
  {
    "date": "2021-07-16",
    "time": "11:47:11",
    "num": 7
  },
  {
    "date": "2021-07-17",
    "time": "13:13:40",
    "num": 8
  },
  {
    "date": "2021-07-18",
    "time": "14:43:24",
    "num": 9
  },
  {
    "date": "2021-07-19",
    "time": "16:16:36",
    "num": 10
  },
  {
    "date": "2021-07-20",
    "time": "17:50:53",
    "num": 11
  },
  {
    "date": "2021-07-21",
    "time": "19:19:13",
    "num": 12
  },
  {
    "date": "2021-07-22",
    "time": "20:31:21",
    "num": 13
  },
  {
    "date": "2021-07-23",
    "time": "21:21:44",
    "num": 14
  },
  {
    "date": "2021-07-24",
    "time": "21:54:08",
    "num": 15
  },
  {
    "date": "2021-07-25",
    "time": "22:15:18",
    "num": 16
  },
  {
    "date": "2021-07-26",
    "time": "22:30:10",
    "num": 17
  },
  {
    "date": "2021-07-27",
    "time": "22:41:38",
    "num": 18
  },
  {
    "date": "2021-07-28",
    "time": "22:51:26",
    "num": 19
  },
  {
    "date": "2021-07-29",
    "time": "23:00:41",
    "num": 20
  },
  {
    "date": "2021-07-30",
    "time": "23:10:21",
    "num": 21
  },
  {
    "date": "2021-07-31",
    "time": "23:21:25",
    "num": 22
  },
  {
    "date": "2021-08-01",
    "time": "23:35:06",
    "num": 23
  },
  {
    "date": "2021-08-02",
    "time": "23:53:08",
    "num": 24
  },
  {
    "date": "2021-08-03",
    "time": "00:00:00",
    "num": 24
  },
  {
    "date": "2021-08-04",
    "time": "00:18:04",
    "num": 25
  },
  {
    "date": "2021-08-05",
    "time": "00:53:14",
    "num": 26
  },
  {
    "date": "2021-08-06",
    "time": "01:41:54",
    "num": 27
  },
  {
    "date": "2021-08-07",
    "time": "02:44:54",
    "num": 28
  },
  {
    "date": "2021-08-08",
    "time": "03:59:25",
    "num": 29
  },
  {
    "date": "2021-08-08",
    "time": "16:50:01",
    "num": 1
  },
  {
    "date": "2021-08-09",
    "time": "05:20:42",
    "num": 2
  },
  {
    "date": "2021-08-10",
    "time": "06:44:46",
    "num": 3
  },
  {
    "date": "2021-08-11",
    "time": "08:09:35",
    "num": 4
  },
  {
    "date": "2021-08-12",
    "time": "09:34:50",
    "num": 5
  },
  {
    "date": "2021-08-13",
    "time": "11:01:11",
    "num": 6
  },
  {
    "date": "2021-08-14",
    "time": "12:29:42",
    "num": 7
  },
  {
    "date": "2021-08-15",
    "time": "14:00:53",
    "num": 8
  },
  {
    "date": "2021-08-16",
    "time": "15:33:26",
    "num": 9
  },
  {
    "date": "2021-08-17",
    "time": "17:02:29",
    "num": 10
  },
  {
    "date": "2021-08-18",
    "time": "18:19:16",
    "num": 11
  },
  {
    "date": "2021-08-19",
    "time": "19:16:16",
    "num": 12
  },
  {
    "date": "2021-08-20",
    "time": "19:54:02",
    "num": 13
  },
  {
    "date": "2021-08-21",
    "time": "20:18:33",
    "num": 14
  },
  {
    "date": "2021-08-22",
    "time": "20:35:20",
    "num": 15
  },
  {
    "date": "2021-08-23",
    "time": "20:47:50",
    "num": 16
  },
  {
    "date": "2021-08-24",
    "time": "20:58:05",
    "num": 17
  },
  {
    "date": "2021-08-25",
    "time": "21:07:23",
    "num": 18
  },
  {
    "date": "2021-08-26",
    "time": "21:16:44",
    "num": 19
  },
  {
    "date": "2021-08-27",
    "time": "21:27:03",
    "num": 20
  },
  {
    "date": "2021-08-28",
    "time": "21:39:25",
    "num": 21
  },
  {
    "date": "2021-08-29",
    "time": "21:55:20",
    "num": 22
  },
  {
    "date": "2021-08-30",
    "time": "22:16:58",
    "num": 23
  },
  {
    "date": "2021-08-31",
    "time": "22:47:22",
    "num": 24
  },
  {
    "date": "2021-09-01",
    "time": "23:30:04",
    "num": 25
  },
  {
    "date": "2021-09-03",
    "time": "00:27:17",
    "num": 26
  },
  {
    "date": "2021-09-04",
    "time": "01:37:49",
    "num": 27
  },
  {
    "date": "2021-09-05",
    "time": "02:57:34",
    "num": 28
  },
  {
    "date": "2021-09-06",
    "time": "04:22:05",
    "num": 29
  },
  {
    "date": "2021-09-07",
    "time": "03:51:39",
    "num": 1
  },
  {
    "date": "2021-09-07",
    "time": "05:48:30",
    "num": 2
  },
  {
    "date": "2021-09-08",
    "time": "07:15:45",
    "num": 3
  },
  {
    "date": "2021-09-09",
    "time": "08:44:03",
    "num": 4
  },
  {
    "date": "2021-09-10",
    "time": "10:14:11",
    "num": 5
  },
  {
    "date": "2021-09-11",
    "time": "11:46:37",
    "num": 6
  },
  {
    "date": "2021-09-12",
    "time": "13:20:28",
    "num": 7
  },
  {
    "date": "2021-09-13",
    "time": "14:51:45",
    "num": 8
  },
  {
    "date": "2021-09-14",
    "time": "16:12:38",
    "num": 9
  },
  {
    "date": "2021-09-15",
    "time": "17:14:50",
    "num": 10
  },
  {
    "date": "2021-09-16",
    "time": "17:56:53",
    "num": 11
  },
  {
    "date": "2021-09-17",
    "time": "18:24:01",
    "num": 12
  },
  {
    "date": "2021-09-18",
    "time": "18:42:13",
    "num": 13
  },
  {
    "date": "2021-09-19",
    "time": "18:55:23",
    "num": 14
  },
  {
    "date": "2021-09-20",
    "time": "19:05:51",
    "num": 15
  },
  {
    "date": "2021-09-21",
    "time": "19:15:02",
    "num": 16
  },
  {
    "date": "2021-09-22",
    "time": "19:23:57",
    "num": 17
  },
  {
    "date": "2021-09-23",
    "time": "19:33:30",
    "num": 18
  },
  {
    "date": "2021-09-24",
    "time": "19:44:39",
    "num": 19
  },
  {
    "date": "2021-09-25",
    "time": "19:58:40",
    "num": 20
  },
  {
    "date": "2021-09-26",
    "time": "20:17:23",
    "num": 21
  },
  {
    "date": "2021-09-27",
    "time": "20:43:28",
    "num": 22
  },
  {
    "date": "2021-09-28",
    "time": "21:20:18",
    "num": 23
  },
  {
    "date": "2021-09-29",
    "time": "22:10:49",
    "num": 24
  },
  {
    "date": "2021-09-30",
    "time": "23:15:21",
    "num": 25
  },
  {
    "date": "2021-10-01",
    "time": "00:00:00",
    "num": 25
  },
  {
    "date": "2021-10-02",
    "time": "00:30:56",
    "num": 26
  },
  {
    "date": "2021-10-03",
    "time": "01:53:15",
    "num": 27
  },
  {
    "date": "2021-10-04",
    "time": "03:19:00",
    "num": 28
  },
  {
    "date": "2021-10-05",
    "time": "04:46:38",
    "num": 29
  },
  {
    "date": "2021-10-06",
    "time": "06:15:58",
    "num": 30
  },
  {
    "date": "2021-10-06",
    "time": "14:05:16",
    "num": 1
  },
  {
    "date": "2021-10-07",
    "time": "07:47:41",
    "num": 2
  },
  {
    "date": "2021-10-08",
    "time": "09:22:25",
    "num": 3
  },
  {
    "date": "2021-10-09",
    "time": "10:59:40",
    "num": 4
  },
  {
    "date": "2021-10-10",
    "time": "12:36:04",
    "num": 5
  },
  {
    "date": "2021-10-11",
    "time": "14:03:58",
    "num": 6
  },
  {
    "date": "2021-10-12",
    "time": "15:13:39",
    "num": 7
  },
  {
    "date": "2021-10-13",
    "time": "16:01:13",
    "num": 8
  },
  {
    "date": "2021-10-14",
    "time": "16:31:26",
    "num": 9
  },
  {
    "date": "2021-10-15",
    "time": "16:51:05",
    "num": 10
  },
  {
    "date": "2021-10-16",
    "time": "17:04:51",
    "num": 11
  },
  {
    "date": "2021-10-17",
    "time": "17:15:26",
    "num": 12
  },
  {
    "date": "2021-10-18",
    "time": "17:24:26",
    "num": 13
  },
  {
    "date": "2021-10-19",
    "time": "17:32:55",
    "num": 14
  },
  {
    "date": "2021-10-20",
    "time": "17:41:46",
    "num": 15
  },
  {
    "date": "2021-10-21",
    "time": "17:51:51",
    "num": 16
  },
  {
    "date": "2021-10-22",
    "time": "18:04:18",
    "num": 17
  },
  {
    "date": "2021-10-23",
    "time": "18:20:41",
    "num": 18
  },
  {
    "date": "2021-10-24",
    "time": "18:43:18",
    "num": 19
  },
  {
    "date": "2021-10-25",
    "time": "19:15:14",
    "num": 20
  },
  {
    "date": "2021-10-26",
    "time": "19:59:43",
    "num": 21
  },
  {
    "date": "2021-10-27",
    "time": "20:58:05",
    "num": 22
  },
  {
    "date": "2021-10-28",
    "time": "22:08:21",
    "num": 23
  },
  {
    "date": "2021-10-29",
    "time": "23:26:33",
    "num": 24
  },
  {
    "date": "2021-10-31",
    "time": "00:49:07",
    "num": 25
  },
  {
    "date": "2021-11-01",
    "time": "02:14:10",
    "num": 26
  },
  {
    "date": "2021-11-02",
    "time": "03:41:22",
    "num": 27
  },
  {
    "date": "2021-11-03",
    "time": "05:11:27",
    "num": 28
  },
  {
    "date": "2021-11-04",
    "time": "06:45:29",
    "num": 29
  },
  {
    "date": "2021-11-05",
    "time": "00:14:29",
    "num": 1
  },
  {
    "date": "2021-11-05",
    "time": "08:23:55",
    "num": 2
  },
  {
    "date": "2021-11-06",
    "time": "10:04:52",
    "num": 3
  },
  {
    "date": "2021-11-07",
    "time": "11:41:47",
    "num": 4
  },
  {
    "date": "2021-11-08",
    "time": "13:03:19",
    "num": 5
  },
  {
    "date": "2021-11-09",
    "time": "14:00:55",
    "num": 6
  },
  {
    "date": "2021-11-10",
    "time": "14:37:03",
    "num": 7
  },
  {
    "date": "2021-11-11",
    "time": "14:59:36",
    "num": 8
  },
  {
    "date": "2021-11-12",
    "time": "15:14:42",
    "num": 9
  },
  {
    "date": "2021-11-13",
    "time": "15:25:48",
    "num": 10
  },
  {
    "date": "2021-11-14",
    "time": "15:34:53",
    "num": 11
  },
  {
    "date": "2021-11-15",
    "time": "15:43:10",
    "num": 12
  },
  {
    "date": "2021-11-16",
    "time": "15:51:31",
    "num": 13
  },
  {
    "date": "2021-11-17",
    "time": "16:00:50",
    "num": 14
  },
  {
    "date": "2021-11-18",
    "time": "16:12:06",
    "num": 15
  },
  {
    "date": "2021-11-19",
    "time": "16:26:43",
    "num": 16
  },
  {
    "date": "2021-11-20",
    "time": "16:46:42",
    "num": 17
  },
  {
    "date": "2021-11-21",
    "time": "17:14:54",
    "num": 18
  },
  {
    "date": "2021-11-22",
    "time": "17:54:38",
    "num": 19
  },
  {
    "date": "2021-11-23",
    "time": "18:47:57",
    "num": 20
  },
  {
    "date": "2021-11-24",
    "time": "19:53:45",
    "num": 21
  },
  {
    "date": "2021-11-25",
    "time": "21:08:14",
    "num": 22
  },
  {
    "date": "2021-11-26",
    "time": "22:27:25",
    "num": 23
  },
  {
    "date": "2021-11-27",
    "time": "23:48:56",
    "num": 24
  },
  {
    "date": "2021-11-28",
    "time": "00:00:00",
    "num": 24
  },
  {
    "date": "2021-11-29",
    "time": "01:12:09",
    "num": 25
  },
  {
    "date": "2021-11-30",
    "time": "02:37:43",
    "num": 26
  },
  {
    "date": "2021-12-01",
    "time": "04:07:01",
    "num": 27
  },
  {
    "date": "2021-12-02",
    "time": "05:41:25",
    "num": 28
  },
  {
    "date": "2021-12-03",
    "time": "07:21:03",
    "num": 29
  },
  {
    "date": "2021-12-04",
    "time": "09:02:28",
    "num": 30
  },
  {
    "date": "2021-12-04",
    "time": "10:42:54",
    "num": 1
  },
  {
    "date": "2021-12-05",
    "time": "10:35:58",
    "num": 2
  },
  {
    "date": "2021-12-06",
    "time": "11:48:27",
    "num": 3
  },
  {
    "date": "2021-12-07",
    "time": "12:35:29",
    "num": 4
  },
  {
    "date": "2021-12-08",
    "time": "13:04:01",
    "num": 5
  },
  {
    "date": "2021-12-09",
    "time": "13:22:08",
    "num": 6
  },
  {
    "date": "2021-12-10",
    "time": "13:34:46",
    "num": 7
  },
  {
    "date": "2021-12-11",
    "time": "13:44:33",
    "num": 8
  },
  {
    "date": "2021-12-12",
    "time": "13:53:04",
    "num": 9
  },
  {
    "date": "2021-12-13",
    "time": "14:01:18",
    "num": 10
  },
  {
    "date": "2021-12-14",
    "time": "14:10:11",
    "num": 11
  },
  {
    "date": "2021-12-15",
    "time": "14:20:38",
    "num": 12
  },
  {
    "date": "2021-12-16",
    "time": "14:33:55",
    "num": 13
  },
  {
    "date": "2021-12-17",
    "time": "14:51:52",
    "num": 14
  },
  {
    "date": "2021-12-18",
    "time": "15:17:05",
    "num": 15
  },
  {
    "date": "2021-12-19",
    "time": "15:52:54",
    "num": 16
  },
  {
    "date": "2021-12-20",
    "time": "16:42:03",
    "num": 17
  },
  {
    "date": "2021-12-21",
    "time": "17:44:28",
    "num": 18
  },
  {
    "date": "2021-12-22",
    "time": "18:56:41",
    "num": 19
  },
  {
    "date": "2021-12-23",
    "time": "20:14:14",
    "num": 20
  },
  {
    "date": "2021-12-24",
    "time": "21:33:55",
    "num": 21
  },
  {
    "date": "2021-12-25",
    "time": "22:54:31",
    "num": 22
  },
  {
    "date": "2021-12-27",
    "time": "00:16:19",
    "num": 23
  },
  {
    "date": "2021-12-28",
    "time": "01:40:31",
    "num": 24
  },
  {
    "date": "2021-12-29",
    "time": "03:08:45",
    "num": 25
  },
  {
    "date": "2021-12-30",
    "time": "04:42:17",
    "num": 26
  },
  {
    "date": "2021-12-31",
    "time": "06:20:27",
    "num": 27
  }
]
